termnautica/__init__.py
termnautica/__main__.py
termnautica/assets/animations/birds/large/flap/1.txt
termnautica/assets/animations/birds/large/flap/2.txt
termnautica/assets/animations/birds/large/flap/3.txt
termnautica/assets/animations/birds/large/flap/4.txt
termnautica/assets/animations/birds/medium/flap/1.txt
termnautica/assets/animations/birds/medium/flap/2.txt
termnautica/assets/animations/birds/medium/flap/3.txt
termnautica/assets/animations/birds/small/flap/1.txt
termnautica/assets/animations/birds/small/flap/2.txt
termnautica/assets/animations/birds/small/flap/3.txt
termnautica/assets/animations/bubble/float/0.txt
termnautica/assets/animations/bubble/float/1.txt
termnautica/assets/animations/bubble/float/2.txt
termnautica/assets/animations/bubble/float/3.txt
termnautica/assets/animations/bubble/float/4.txt
termnautica/assets/animations/bubble/pop/1.txt
termnautica/assets/animations/bubble/pop/2.txt
termnautica/assets/animations/bubble/pop/3.txt
termnautica/assets/animations/kelp/1.txt
termnautica/assets/animations/kelp/2.txt
termnautica/assets/animations/kelp/3.txt
termnautica/assets/music/main.mp3
termnautica/assets/sounds/ambient/stumble.wav
termnautica/assets/sounds/bird.wav
termnautica/assets/sounds/collect/coal.wav
termnautica/assets/sounds/collect/crystal.wav
termnautica/assets/sounds/collect/default.wav
termnautica/assets/sounds/collect/diamond.wav
termnautica/assets/sounds/collect/fish.wav
termnautica/assets/sounds/collect/nemo.wav
termnautica/assets/sounds/collect/ore.wav
termnautica/assets/sounds/collect/small_fish.wav
termnautica/assets/sounds/crystal2.wav
termnautica/assets/sounds/hit.wav
termnautica/assets/sounds/hostile_fish_lurk.wav
termnautica/assets/sounds/hurt2.wav
termnautica/assets/sounds/ui/health/heal.wav
termnautica/assets/sounds/ui/health/hurt.wav
termnautica/assets/sounds/ui/oxygen/breathe.wav
termnautica/assets/sounds/ui/oxygen/bubble.wav
termnautica/assets/sprites/airlock/closed.txt
termnautica/assets/sprites/airlock/open.txt
havsalt_termnautica-0.1.0.dev9.dist-info/WHEEL
havsalt_termnautica-0.1.0.dev9.dist-info/entry_points.txt
havsalt_termnautica-0.1.0.dev9.dist-info/METADATA
havsalt_termnautica-0.1.0.dev9.dist-info/RECORD
