Metadata-Version: 2.3
Name: havsalt-termnautica
Version: 0.1.0.dev9
Summary: Underwater game made using `charz`
Author: Havsalt
Author-email: Havsalt <77575424+Havsalt@users.noreply.github.com>
License: MIT License
Requires-Dist: charz-rust>=0.2.3
Requires-Dist: charz[all]~=0.1.0
Requires-Dist: pygame~=2.6
Requires-Python: >=3.13
